pgpl/__init__.py
pgpl/__main__.py
pgpl/i18n.py
pgpl/packageinit.py
pgpl-0.0.11.dist-info/METADATA
pgpl-0.0.11.dist-info/WHEEL
pgpl-0.0.11.dist-info/RECORD
